pykage/.DS_Store
pykage/__init__.py
pykage/build/exe.macosx-10.9-universal2-3.10/command/__init__.py
pykage/build/exe.macosx-10.9-universal2-3.10/command/add_command.py
pykage/build/exe.macosx-10.9-universal2-3.10/command/base_cmd.py
pykage/build/exe.macosx-10.9-universal2-3.10/command/init_command.py
pykage/build/exe.macosx-10.9-universal2-3.10/command/install_command.py
pykage/build/exe.macosx-10.9-universal2-3.10/command/run_command.py
pykage/build/exe.macosx-10.9-universal2-3.10/lib/Python
pykage/build/exe.macosx-10.9-universal2-3.10/lib/_asyncio.cpython-310-darwin.so
pykage/build/exe.macosx-10.9-universal2-3.10/lib/_bisect.cpython-310-darwin.so
pykage/build/exe.macosx-10.9-universal2-3.10/lib/_blake2.cpython-310-darwin.so
pykage/build/exe.macosx-10.9-universal2-3.10/lib/_bz2.cpython-310-darwin.so
pykage/build/exe.macosx-10.9-universal2-3.10/lib/_codecs_cn.cpython-310-darwin.so
pykage/build/exe.macosx-10.9-universal2-3.10/lib/_codecs_hk.cpython-310-darwin.so
pykage/build/exe.macosx-10.9-universal2-3.10/lib/_codecs_iso2022.cpython-310-darwin.so
pykage/build/exe.macosx-10.9-universal2-3.10/lib/_codecs_jp.cpython-310-darwin.so
pykage/build/exe.macosx-10.9-universal2-3.10/lib/_codecs_kr.cpython-310-darwin.so
pykage/build/exe.macosx-10.9-universal2-3.10/lib/_codecs_tw.cpython-310-darwin.so
pykage/build/exe.macosx-10.9-universal2-3.10/lib/_contextvars.cpython-310-darwin.so
pykage/build/exe.macosx-10.9-universal2-3.10/lib/_csv.cpython-310-darwin.so
pykage/build/exe.macosx-10.9-universal2-3.10/lib/_ctypes.cpython-310-darwin.so
pykage/build/exe.macosx-10.9-universal2-3.10/lib/_datetime.cpython-310-darwin.so
pykage/build/exe.macosx-10.9-universal2-3.10/lib/_decimal.cpython-310-darwin.so
pykage/build/exe.macosx-10.9-universal2-3.10/lib/_elementtree.cpython-310-darwin.so
pykage/build/exe.macosx-10.9-universal2-3.10/lib/_hashlib.cpython-310-darwin.so
pykage/build/exe.macosx-10.9-universal2-3.10/lib/_heapq.cpython-310-darwin.so
pykage-0.2.dist-info/LICENSE.txt
pykage-0.2.dist-info/WHEEL
pykage-0.2.dist-info/METADATA
pykage-0.2.dist-info/RECORD
